{
  "expireTime": 9007200887118514000,
  "key": "transformer-remark-markdown-html-ast-6369de1d55b2a69cbb1a8ea52aa2e235-gatsby-remark-autolink-headersgatsby-remark-prismjs-",
  "val": {
    "type": "root",
    "children": [
      {
        "type": "element",
        "tagName": "h1",
        "properties": { "id": "npmrc5", "style": "position:relative;" },
        "children": [
          {
            "type": "element",
            "tagName": "a",
            "properties": {
              "href": "#npmrc5",
              "aria-label": "npmrc5 permalink",
              "class": "header-link-class before"
            },
            "children": [
              {
                "type": "raw",
                "value": "<svg aria-hidden=\"true\" height=\"20\" version=\"1.1\" viewBox=\"0 0 16 16\" width=\"20\"><path fill-rule=\"evenodd\" d=\"M4 9h1v1H4c-1.5 0-3-1.69-3-3.5S2.55 3 4 3h4c1.45 0 3 1.69 3 3.5 0 1.41-.91 2.72-2 3.25V8.59c.58-.45 1-1.27 1-2.09C10 5.22 8.98 4 8 4H4c-.98 0-2 1.22-2 2.5S3 9 4 9zm9-3h-1v1h1c1 0 2 1.22 2 2.5S13.98 12 13 12H9c-.98 0-2-1.22-2-2.5 0-.83.42-1.64 1-2.09V6.25c-1.09.53-2 1.84-2 3.25C6 11.31 7.55 13 9 13h4c1.45 0 3-1.69 3-3.5S14.5 6 13 6z\"></path></svg>"
              }
            ]
          },
          {
            "type": "text",
            "value": "npmrc(5)",
            "position": {
              "start": { "line": 2, "column": 3, "offset": 3 },
              "end": { "line": 2, "column": 11, "offset": 11 }
            }
          }
        ],
        "position": {
          "start": { "line": 2, "column": 1, "offset": 1 },
          "end": { "line": 2, "column": 11, "offset": 11 }
        }
      },
      { "type": "text", "value": "\n" },
      {
        "type": "element",
        "tagName": "h2",
        "properties": {
          "id": "the-npm-config-files",
          "style": "position:relative;"
        },
        "children": [
          {
            "type": "element",
            "tagName": "a",
            "properties": {
              "href": "#the-npm-config-files",
              "aria-label": "the npm config files permalink",
              "class": "header-link-class before"
            },
            "children": [
              {
                "type": "raw",
                "value": "<svg aria-hidden=\"true\" height=\"20\" version=\"1.1\" viewBox=\"0 0 16 16\" width=\"20\"><path fill-rule=\"evenodd\" d=\"M4 9h1v1H4c-1.5 0-3-1.69-3-3.5S2.55 3 4 3h4c1.45 0 3 1.69 3 3.5 0 1.41-.91 2.72-2 3.25V8.59c.58-.45 1-1.27 1-2.09C10 5.22 8.98 4 8 4H4c-.98 0-2 1.22-2 2.5S3 9 4 9zm9-3h-1v1h1c1 0 2 1.22 2 2.5S13.98 12 13 12H9c-.98 0-2-1.22-2-2.5 0-.83.42-1.64 1-2.09V6.25c-1.09.53-2 1.84-2 3.25C6 11.31 7.55 13 9 13h4c1.45 0 3-1.69 3-3.5S14.5 6 13 6z\"></path></svg>"
              }
            ]
          },
          {
            "type": "text",
            "value": "The npm config files",
            "position": {
              "start": { "line": 4, "column": 4, "offset": 16 },
              "end": { "line": 4, "column": 24, "offset": 36 }
            }
          }
        ],
        "position": {
          "start": { "line": 4, "column": 1, "offset": 13 },
          "end": { "line": 4, "column": 24, "offset": 36 }
        }
      },
      { "type": "text", "value": "\n" },
      {
        "type": "element",
        "tagName": "h3",
        "properties": { "id": "description", "style": "position:relative;" },
        "children": [
          {
            "type": "element",
            "tagName": "a",
            "properties": {
              "href": "#description",
              "aria-label": "description permalink",
              "class": "header-link-class before"
            },
            "children": [
              {
                "type": "raw",
                "value": "<svg aria-hidden=\"true\" height=\"20\" version=\"1.1\" viewBox=\"0 0 16 16\" width=\"20\"><path fill-rule=\"evenodd\" d=\"M4 9h1v1H4c-1.5 0-3-1.69-3-3.5S2.55 3 4 3h4c1.45 0 3 1.69 3 3.5 0 1.41-.91 2.72-2 3.25V8.59c.58-.45 1-1.27 1-2.09C10 5.22 8.98 4 8 4H4c-.98 0-2 1.22-2 2.5S3 9 4 9zm9-3h-1v1h1c1 0 2 1.22 2 2.5S13.98 12 13 12H9c-.98 0-2-1.22-2-2.5 0-.83.42-1.64 1-2.09V6.25c-1.09.53-2 1.84-2 3.25C6 11.31 7.55 13 9 13h4c1.45 0 3-1.69 3-3.5S14.5 6 13 6z\"></path></svg>"
              }
            ]
          },
          {
            "type": "text",
            "value": "Description",
            "position": {
              "start": { "line": 6, "column": 5, "offset": 42 },
              "end": { "line": 6, "column": 16, "offset": 53 }
            }
          }
        ],
        "position": {
          "start": { "line": 6, "column": 1, "offset": 38 },
          "end": { "line": 6, "column": 16, "offset": 53 }
        }
      },
      { "type": "text", "value": "\n" },
      {
        "type": "element",
        "tagName": "p",
        "properties": {},
        "children": [
          {
            "type": "text",
            "value": "npm gets its config settings from the command line, environment\nvariables, and ",
            "position": {
              "start": { "line": 8, "column": 1, "offset": 55 },
              "end": { "line": 9, "column": 16, "offset": 134 }
            }
          },
          {
            "type": "raw",
            "value": "<code class=\"language-text\">npmrc</code>",
            "position": {
              "start": { "line": 9, "column": 16, "offset": 134 },
              "end": { "line": 9, "column": 23, "offset": 141 }
            }
          },
          {
            "type": "text",
            "value": " files.",
            "position": {
              "start": { "line": 9, "column": 23, "offset": 141 },
              "end": { "line": 9, "column": 30, "offset": 148 }
            }
          }
        ],
        "position": {
          "start": { "line": 8, "column": 1, "offset": 55 },
          "end": { "line": 9, "column": 30, "offset": 148 }
        }
      },
      { "type": "text", "value": "\n" },
      {
        "type": "element",
        "tagName": "p",
        "properties": {},
        "children": [
          {
            "type": "text",
            "value": "The ",
            "position": {
              "start": { "line": 11, "column": 1, "offset": 150 },
              "end": { "line": 11, "column": 5, "offset": 154 }
            }
          },
          {
            "type": "raw",
            "value": "<code class=\"language-text\">npm config</code>",
            "position": {
              "start": { "line": 11, "column": 5, "offset": 154 },
              "end": { "line": 11, "column": 17, "offset": 166 }
            }
          },
          {
            "type": "text",
            "value": " command can be used to update and edit the contents\nof the user and global npmrc files.",
            "position": {
              "start": { "line": 11, "column": 17, "offset": 166 },
              "end": { "line": 12, "column": 36, "offset": 254 }
            }
          }
        ],
        "position": {
          "start": { "line": 11, "column": 1, "offset": 150 },
          "end": { "line": 12, "column": 36, "offset": 254 }
        }
      },
      { "type": "text", "value": "\n" },
      {
        "type": "element",
        "tagName": "p",
        "properties": {},
        "children": [
          {
            "type": "text",
            "value": "For a list of available configuration options, see ",
            "position": {
              "start": { "line": 14, "column": 1, "offset": 256 },
              "end": { "line": 14, "column": 52, "offset": 307 }
            }
          },
          {
            "type": "element",
            "tagName": "a",
            "properties": { "href": "/using-npm/config" },
            "children": [
              {
                "type": "text",
                "value": "config",
                "position": {
                  "start": { "line": 14, "column": 53, "offset": 308 },
                  "end": { "line": 14, "column": 59, "offset": 314 }
                }
              }
            ],
            "position": {
              "start": { "line": 14, "column": 52, "offset": 307 },
              "end": { "line": 14, "column": 79, "offset": 334 }
            }
          },
          {
            "type": "text",
            "value": ".",
            "position": {
              "start": { "line": 14, "column": 79, "offset": 334 },
              "end": { "line": 14, "column": 80, "offset": 335 }
            }
          }
        ],
        "position": {
          "start": { "line": 14, "column": 1, "offset": 256 },
          "end": { "line": 14, "column": 80, "offset": 335 }
        }
      },
      { "type": "text", "value": "\n" },
      {
        "type": "element",
        "tagName": "h3",
        "properties": { "id": "files", "style": "position:relative;" },
        "children": [
          {
            "type": "element",
            "tagName": "a",
            "properties": {
              "href": "#files",
              "aria-label": "files permalink",
              "class": "header-link-class before"
            },
            "children": [
              {
                "type": "raw",
                "value": "<svg aria-hidden=\"true\" height=\"20\" version=\"1.1\" viewBox=\"0 0 16 16\" width=\"20\"><path fill-rule=\"evenodd\" d=\"M4 9h1v1H4c-1.5 0-3-1.69-3-3.5S2.55 3 4 3h4c1.45 0 3 1.69 3 3.5 0 1.41-.91 2.72-2 3.25V8.59c.58-.45 1-1.27 1-2.09C10 5.22 8.98 4 8 4H4c-.98 0-2 1.22-2 2.5S3 9 4 9zm9-3h-1v1h1c1 0 2 1.22 2 2.5S13.98 12 13 12H9c-.98 0-2-1.22-2-2.5 0-.83.42-1.64 1-2.09V6.25c-1.09.53-2 1.84-2 3.25C6 11.31 7.55 13 9 13h4c1.45 0 3-1.69 3-3.5S14.5 6 13 6z\"></path></svg>"
              }
            ]
          },
          {
            "type": "text",
            "value": "Files",
            "position": {
              "start": { "line": 16, "column": 5, "offset": 341 },
              "end": { "line": 16, "column": 10, "offset": 346 }
            }
          }
        ],
        "position": {
          "start": { "line": 16, "column": 1, "offset": 337 },
          "end": { "line": 16, "column": 10, "offset": 346 }
        }
      },
      { "type": "text", "value": "\n" },
      {
        "type": "element",
        "tagName": "p",
        "properties": {},
        "children": [
          {
            "type": "text",
            "value": "The four relevant files are:",
            "position": {
              "start": { "line": 18, "column": 1, "offset": 348 },
              "end": { "line": 18, "column": 29, "offset": 376 }
            }
          }
        ],
        "position": {
          "start": { "line": 18, "column": 1, "offset": 348 },
          "end": { "line": 18, "column": 29, "offset": 376 }
        }
      },
      { "type": "text", "value": "\n" },
      {
        "type": "element",
        "tagName": "ul",
        "properties": {},
        "children": [
          { "type": "text", "value": "\n" },
          {
            "type": "element",
            "tagName": "li",
            "properties": {},
            "children": [
              {
                "type": "text",
                "value": "per-project config file (/path/to/my/project/.npmrc)",
                "position": {
                  "start": { "line": 20, "column": 3, "offset": 380 },
                  "end": { "line": 20, "column": 55, "offset": 432 }
                }
              }
            ],
            "position": {
              "start": { "line": 20, "column": 1, "offset": 378 },
              "end": { "line": 20, "column": 55, "offset": 432 }
            }
          },
          { "type": "text", "value": "\n" },
          {
            "type": "element",
            "tagName": "li",
            "properties": {},
            "children": [
              {
                "type": "text",
                "value": "per-user config file (~/.npmrc)",
                "position": {
                  "start": { "line": 21, "column": 3, "offset": 435 },
                  "end": { "line": 21, "column": 34, "offset": 466 }
                }
              }
            ],
            "position": {
              "start": { "line": 21, "column": 1, "offset": 433 },
              "end": { "line": 21, "column": 34, "offset": 466 }
            }
          },
          { "type": "text", "value": "\n" },
          {
            "type": "element",
            "tagName": "li",
            "properties": {},
            "children": [
              {
                "type": "text",
                "value": "global config file ($PREFIX/etc/npmrc)",
                "position": {
                  "start": { "line": 22, "column": 3, "offset": 469 },
                  "end": { "line": 22, "column": 41, "offset": 507 }
                }
              }
            ],
            "position": {
              "start": { "line": 22, "column": 1, "offset": 467 },
              "end": { "line": 22, "column": 41, "offset": 507 }
            }
          },
          { "type": "text", "value": "\n" },
          {
            "type": "element",
            "tagName": "li",
            "properties": {},
            "children": [
              {
                "type": "text",
                "value": "npm builtin config file (/path/to/npm/npmrc)",
                "position": {
                  "start": { "line": 23, "column": 3, "offset": 510 },
                  "end": { "line": 23, "column": 47, "offset": 554 }
                }
              }
            ],
            "position": {
              "start": { "line": 23, "column": 1, "offset": 508 },
              "end": { "line": 23, "column": 47, "offset": 554 }
            }
          },
          { "type": "text", "value": "\n" }
        ],
        "position": {
          "start": { "line": 20, "column": 1, "offset": 378 },
          "end": { "line": 23, "column": 47, "offset": 554 }
        }
      },
      { "type": "text", "value": "\n" },
      {
        "type": "element",
        "tagName": "p",
        "properties": {},
        "children": [
          {
            "type": "text",
            "value": "All npm config files are an ini-formatted list of ",
            "position": {
              "start": { "line": 25, "column": 1, "offset": 556 },
              "end": { "line": 25, "column": 51, "offset": 606 }
            }
          },
          {
            "type": "raw",
            "value": "<code class=\"language-text\">key = value</code>",
            "position": {
              "start": { "line": 25, "column": 51, "offset": 606 },
              "end": { "line": 25, "column": 64, "offset": 619 }
            }
          },
          {
            "type": "text",
            "value": "\nparameters. Environment variables can be replaced using\n",
            "position": {
              "start": { "line": 25, "column": 64, "offset": 619 },
              "end": { "line": 27, "column": 1, "offset": 676 }
            }
          },
          {
            "type": "raw",
            "value": "<code class=\"language-text\">${VARIABLE_NAME}</code>",
            "position": {
              "start": { "line": 27, "column": 1, "offset": 676 },
              "end": { "line": 27, "column": 19, "offset": 694 }
            }
          },
          {
            "type": "text",
            "value": ". For example:",
            "position": {
              "start": { "line": 27, "column": 19, "offset": 694 },
              "end": { "line": 27, "column": 33, "offset": 708 }
            }
          }
        ],
        "position": {
          "start": { "line": 25, "column": 1, "offset": 556 },
          "end": { "line": 27, "column": 33, "offset": 708 }
        }
      },
      { "type": "text", "value": "\n" },
      {
        "type": "raw",
        "value": "<div class=\"gatsby-highlight\" data-language=\"bash\"><pre class=\"language-bash\"><code class=\"language-bash\">prefix <span class=\"token operator\">=</span> <span class=\"token variable\">${<span class=\"token environment constant\">HOME</span>}</span>/.npm-packages</code></pre></div>",
        "position": {
          "start": { "line": 29, "column": 1, "offset": 710 },
          "end": { "line": 31, "column": 4, "offset": 752 }
        }
      },
      { "type": "text", "value": "\n" },
      {
        "type": "element",
        "tagName": "p",
        "properties": {},
        "children": [
          {
            "type": "text",
            "value": "Each of these files is loaded, and config options are resolved in\npriority order. For example, a setting in the userconfig file would\noverride the setting in the globalconfig file.",
            "position": {
              "start": { "line": 33, "column": 1, "offset": 754 },
              "end": { "line": 35, "column": 47, "offset": 934 }
            }
          }
        ],
        "position": {
          "start": { "line": 33, "column": 1, "offset": 754 },
          "end": { "line": 35, "column": 47, "offset": 934 }
        }
      },
      { "type": "text", "value": "\n" },
      {
        "type": "element",
        "tagName": "p",
        "properties": {},
        "children": [
          {
            "type": "text",
            "value": "Array values are specified by adding \"[]\" after the key name. For\nexample:",
            "position": {
              "start": { "line": 37, "column": 1, "offset": 936 },
              "end": { "line": 38, "column": 9, "offset": 1010 }
            }
          }
        ],
        "position": {
          "start": { "line": 37, "column": 1, "offset": 936 },
          "end": { "line": 38, "column": 9, "offset": 1010 }
        }
      },
      { "type": "text", "value": "\n" },
      {
        "type": "raw",
        "value": "<div class=\"gatsby-highlight\" data-language=\"bash\"><pre class=\"language-bash\"><code class=\"language-bash\">key<span class=\"token punctuation\">[</span><span class=\"token punctuation\">]</span> <span class=\"token operator\">=</span> <span class=\"token string\">\"first value\"</span>\nkey<span class=\"token punctuation\">[</span><span class=\"token punctuation\">]</span> <span class=\"token operator\">=</span> <span class=\"token string\">\"second value\"</span></code></pre></div>",
        "position": {
          "start": { "line": 40, "column": 1, "offset": 1012 },
          "end": { "line": 43, "column": 4, "offset": 1068 }
        }
      },
      { "type": "text", "value": "\n" },
      {
        "type": "element",
        "tagName": "h4",
        "properties": { "id": "comments", "style": "position:relative;" },
        "children": [
          {
            "type": "element",
            "tagName": "a",
            "properties": {
              "href": "#comments",
              "aria-label": "comments permalink",
              "class": "header-link-class before"
            },
            "children": [
              {
                "type": "raw",
                "value": "<svg aria-hidden=\"true\" height=\"20\" version=\"1.1\" viewBox=\"0 0 16 16\" width=\"20\"><path fill-rule=\"evenodd\" d=\"M4 9h1v1H4c-1.5 0-3-1.69-3-3.5S2.55 3 4 3h4c1.45 0 3 1.69 3 3.5 0 1.41-.91 2.72-2 3.25V8.59c.58-.45 1-1.27 1-2.09C10 5.22 8.98 4 8 4H4c-.98 0-2 1.22-2 2.5S3 9 4 9zm9-3h-1v1h1c1 0 2 1.22 2 2.5S13.98 12 13 12H9c-.98 0-2-1.22-2-2.5 0-.83.42-1.64 1-2.09V6.25c-1.09.53-2 1.84-2 3.25C6 11.31 7.55 13 9 13h4c1.45 0 3-1.69 3-3.5S14.5 6 13 6z\"></path></svg>"
              }
            ]
          },
          {
            "type": "text",
            "value": "Comments",
            "position": {
              "start": { "line": 45, "column": 6, "offset": 1075 },
              "end": { "line": 45, "column": 14, "offset": 1083 }
            }
          }
        ],
        "position": {
          "start": { "line": 45, "column": 1, "offset": 1070 },
          "end": { "line": 45, "column": 14, "offset": 1083 }
        }
      },
      { "type": "text", "value": "\n" },
      {
        "type": "element",
        "tagName": "p",
        "properties": {},
        "children": [
          {
            "type": "text",
            "value": "Lines in ",
            "position": {
              "start": { "line": 47, "column": 1, "offset": 1085 },
              "end": { "line": 47, "column": 10, "offset": 1094 }
            }
          },
          {
            "type": "raw",
            "value": "<code class=\"language-text\">.npmrc</code>",
            "position": {
              "start": { "line": 47, "column": 10, "offset": 1094 },
              "end": { "line": 47, "column": 18, "offset": 1102 }
            }
          },
          {
            "type": "text",
            "value": " files are interpreted as comments when they begin with a ",
            "position": {
              "start": { "line": 47, "column": 18, "offset": 1102 },
              "end": { "line": 47, "column": 76, "offset": 1160 }
            }
          },
          {
            "type": "raw",
            "value": "<code class=\"language-text\">;</code>",
            "position": {
              "start": { "line": 47, "column": 76, "offset": 1160 },
              "end": { "line": 47, "column": 79, "offset": 1163 }
            }
          },
          {
            "type": "text",
            "value": " or ",
            "position": {
              "start": { "line": 47, "column": 79, "offset": 1163 },
              "end": { "line": 47, "column": 83, "offset": 1167 }
            }
          },
          {
            "type": "raw",
            "value": "<code class=\"language-text\">#</code>",
            "position": {
              "start": { "line": 47, "column": 83, "offset": 1167 },
              "end": { "line": 47, "column": 86, "offset": 1170 }
            }
          },
          {
            "type": "text",
            "value": " character. ",
            "position": {
              "start": { "line": 47, "column": 86, "offset": 1170 },
              "end": { "line": 47, "column": 98, "offset": 1182 }
            }
          },
          {
            "type": "raw",
            "value": "<code class=\"language-text\">.npmrc</code>",
            "position": {
              "start": { "line": 47, "column": 98, "offset": 1182 },
              "end": { "line": 47, "column": 106, "offset": 1190 }
            }
          },
          {
            "type": "text",
            "value": " files are parsed by ",
            "position": {
              "start": { "line": 47, "column": 106, "offset": 1190 },
              "end": { "line": 47, "column": 127, "offset": 1211 }
            }
          },
          {
            "type": "element",
            "tagName": "a",
            "properties": { "href": "https://github.com/npm/ini" },
            "children": [
              {
                "type": "text",
                "value": "npm/ini",
                "position": {
                  "start": { "line": 47, "column": 128, "offset": 1212 },
                  "end": { "line": 47, "column": 135, "offset": 1219 }
                }
              }
            ],
            "position": {
              "start": { "line": 47, "column": 127, "offset": 1211 },
              "end": { "line": 47, "column": 164, "offset": 1248 }
            }
          },
          {
            "type": "text",
            "value": ", which specifies this comment syntax.",
            "position": {
              "start": { "line": 47, "column": 164, "offset": 1248 },
              "end": { "line": 47, "column": 202, "offset": 1286 }
            }
          }
        ],
        "position": {
          "start": { "line": 47, "column": 1, "offset": 1085 },
          "end": { "line": 47, "column": 202, "offset": 1286 }
        }
      },
      { "type": "text", "value": "\n" },
      {
        "type": "element",
        "tagName": "p",
        "properties": {},
        "children": [
          {
            "type": "text",
            "value": "For example:",
            "position": {
              "start": { "line": 49, "column": 1, "offset": 1288 },
              "end": { "line": 49, "column": 13, "offset": 1300 }
            }
          }
        ],
        "position": {
          "start": { "line": 49, "column": 1, "offset": 1288 },
          "end": { "line": 49, "column": 13, "offset": 1300 }
        }
      },
      { "type": "text", "value": "\n" },
      {
        "type": "raw",
        "value": "<div class=\"gatsby-highlight\" data-language=\"bash\"><pre class=\"language-bash\"><code class=\"language-bash\"><span class=\"token comment\"># last modified: 01 Jan 2016</span>\n<span class=\"token punctuation\">;</span> Set a new registry <span class=\"token keyword\">for</span> a scoped package\n@myscope:registry<span class=\"token operator\">=</span>https://mycustomregistry.example.org</code></pre></div>",
        "position": {
          "start": { "line": 51, "column": 1, "offset": 1302 },
          "end": { "line": 55, "column": 4, "offset": 1439 }
        }
      },
      { "type": "text", "value": "\n" },
      {
        "type": "element",
        "tagName": "h4",
        "properties": {
          "id": "per-project-config-file",
          "style": "position:relative;"
        },
        "children": [
          {
            "type": "element",
            "tagName": "a",
            "properties": {
              "href": "#per-project-config-file",
              "aria-label": "per project config file permalink",
              "class": "header-link-class before"
            },
            "children": [
              {
                "type": "raw",
                "value": "<svg aria-hidden=\"true\" height=\"20\" version=\"1.1\" viewBox=\"0 0 16 16\" width=\"20\"><path fill-rule=\"evenodd\" d=\"M4 9h1v1H4c-1.5 0-3-1.69-3-3.5S2.55 3 4 3h4c1.45 0 3 1.69 3 3.5 0 1.41-.91 2.72-2 3.25V8.59c.58-.45 1-1.27 1-2.09C10 5.22 8.98 4 8 4H4c-.98 0-2 1.22-2 2.5S3 9 4 9zm9-3h-1v1h1c1 0 2 1.22 2 2.5S13.98 12 13 12H9c-.98 0-2-1.22-2-2.5 0-.83.42-1.64 1-2.09V6.25c-1.09.53-2 1.84-2 3.25C6 11.31 7.55 13 9 13h4c1.45 0 3-1.69 3-3.5S14.5 6 13 6z\"></path></svg>"
              }
            ]
          },
          {
            "type": "text",
            "value": "Per-project config file",
            "position": {
              "start": { "line": 57, "column": 6, "offset": 1446 },
              "end": { "line": 57, "column": 29, "offset": 1469 }
            }
          }
        ],
        "position": {
          "start": { "line": 57, "column": 1, "offset": 1441 },
          "end": { "line": 57, "column": 29, "offset": 1469 }
        }
      },
      { "type": "text", "value": "\n" },
      {
        "type": "element",
        "tagName": "p",
        "properties": {},
        "children": [
          {
            "type": "text",
            "value": "When working locally in a project, a ",
            "position": {
              "start": { "line": 59, "column": 1, "offset": 1471 },
              "end": { "line": 59, "column": 38, "offset": 1508 }
            }
          },
          {
            "type": "raw",
            "value": "<code class=\"language-text\">.npmrc</code>",
            "position": {
              "start": { "line": 59, "column": 38, "offset": 1508 },
              "end": { "line": 59, "column": 46, "offset": 1516 }
            }
          },
          {
            "type": "text",
            "value": " file in the root of the\nproject (ie, a sibling of ",
            "position": {
              "start": { "line": 59, "column": 46, "offset": 1516 },
              "end": { "line": 60, "column": 27, "offset": 1567 }
            }
          },
          {
            "type": "raw",
            "value": "<code class=\"language-text\">node_modules</code>",
            "position": {
              "start": { "line": 60, "column": 27, "offset": 1567 },
              "end": { "line": 60, "column": 41, "offset": 1581 }
            }
          },
          {
            "type": "text",
            "value": " and ",
            "position": {
              "start": { "line": 60, "column": 41, "offset": 1581 },
              "end": { "line": 60, "column": 46, "offset": 1586 }
            }
          },
          {
            "type": "raw",
            "value": "<code class=\"language-text\">package.json</code>",
            "position": {
              "start": { "line": 60, "column": 46, "offset": 1586 },
              "end": { "line": 60, "column": 60, "offset": 1600 }
            }
          },
          {
            "type": "text",
            "value": ") will set\nconfig values specific to this project.",
            "position": {
              "start": { "line": 60, "column": 60, "offset": 1600 },
              "end": { "line": 61, "column": 40, "offset": 1650 }
            }
          }
        ],
        "position": {
          "start": { "line": 59, "column": 1, "offset": 1471 },
          "end": { "line": 61, "column": 40, "offset": 1650 }
        }
      },
      { "type": "text", "value": "\n" },
      {
        "type": "element",
        "tagName": "p",
        "properties": {},
        "children": [
          {
            "type": "text",
            "value": "Note that this only applies to the root of the project that you're\nrunning npm in. It has no effect when your module is published. For\nexample, you can't publish a module that forces itself to install\nglobally, or in a different location.",
            "position": {
              "start": { "line": 63, "column": 1, "offset": 1652 },
              "end": { "line": 66, "column": 38, "offset": 1890 }
            }
          }
        ],
        "position": {
          "start": { "line": 63, "column": 1, "offset": 1652 },
          "end": { "line": 66, "column": 38, "offset": 1890 }
        }
      },
      { "type": "text", "value": "\n" },
      {
        "type": "element",
        "tagName": "p",
        "properties": {},
        "children": [
          {
            "type": "text",
            "value": "Additionally, this file is not read in global mode, such as when running\n",
            "position": {
              "start": { "line": 68, "column": 1, "offset": 1892 },
              "end": { "line": 69, "column": 1, "offset": 1965 }
            }
          },
          {
            "type": "raw",
            "value": "<code class=\"language-text\">npm install -g</code>",
            "position": {
              "start": { "line": 69, "column": 1, "offset": 1965 },
              "end": { "line": 69, "column": 17, "offset": 1981 }
            }
          },
          {
            "type": "text",
            "value": ".",
            "position": {
              "start": { "line": 69, "column": 17, "offset": 1981 },
              "end": { "line": 69, "column": 18, "offset": 1982 }
            }
          }
        ],
        "position": {
          "start": { "line": 68, "column": 1, "offset": 1892 },
          "end": { "line": 69, "column": 18, "offset": 1982 }
        }
      },
      { "type": "text", "value": "\n" },
      {
        "type": "element",
        "tagName": "h4",
        "properties": {
          "id": "per-user-config-file",
          "style": "position:relative;"
        },
        "children": [
          {
            "type": "element",
            "tagName": "a",
            "properties": {
              "href": "#per-user-config-file",
              "aria-label": "per user config file permalink",
              "class": "header-link-class before"
            },
            "children": [
              {
                "type": "raw",
                "value": "<svg aria-hidden=\"true\" height=\"20\" version=\"1.1\" viewBox=\"0 0 16 16\" width=\"20\"><path fill-rule=\"evenodd\" d=\"M4 9h1v1H4c-1.5 0-3-1.69-3-3.5S2.55 3 4 3h4c1.45 0 3 1.69 3 3.5 0 1.41-.91 2.72-2 3.25V8.59c.58-.45 1-1.27 1-2.09C10 5.22 8.98 4 8 4H4c-.98 0-2 1.22-2 2.5S3 9 4 9zm9-3h-1v1h1c1 0 2 1.22 2 2.5S13.98 12 13 12H9c-.98 0-2-1.22-2-2.5 0-.83.42-1.64 1-2.09V6.25c-1.09.53-2 1.84-2 3.25C6 11.31 7.55 13 9 13h4c1.45 0 3-1.69 3-3.5S14.5 6 13 6z\"></path></svg>"
              }
            ]
          },
          {
            "type": "text",
            "value": "Per-user config file",
            "position": {
              "start": { "line": 71, "column": 6, "offset": 1989 },
              "end": { "line": 71, "column": 26, "offset": 2009 }
            }
          }
        ],
        "position": {
          "start": { "line": 71, "column": 1, "offset": 1984 },
          "end": { "line": 71, "column": 26, "offset": 2009 }
        }
      },
      { "type": "text", "value": "\n" },
      {
        "type": "element",
        "tagName": "p",
        "properties": {},
        "children": [
          {
            "type": "raw",
            "value": "<code class=\"language-text\">$HOME/.npmrc</code>",
            "position": {
              "start": { "line": 73, "column": 1, "offset": 2011 },
              "end": { "line": 73, "column": 15, "offset": 2025 }
            }
          },
          {
            "type": "text",
            "value": " (or the ",
            "position": {
              "start": { "line": 73, "column": 15, "offset": 2025 },
              "end": { "line": 73, "column": 24, "offset": 2034 }
            }
          },
          {
            "type": "raw",
            "value": "<code class=\"language-text\">userconfig</code>",
            "position": {
              "start": { "line": 73, "column": 24, "offset": 2034 },
              "end": { "line": 73, "column": 36, "offset": 2046 }
            }
          },
          {
            "type": "text",
            "value": " param, if set in the environment\nor on the command line)",
            "position": {
              "start": { "line": 73, "column": 36, "offset": 2046 },
              "end": { "line": 74, "column": 24, "offset": 2103 }
            }
          }
        ],
        "position": {
          "start": { "line": 73, "column": 1, "offset": 2011 },
          "end": { "line": 74, "column": 24, "offset": 2103 }
        }
      },
      { "type": "text", "value": "\n" },
      {
        "type": "element",
        "tagName": "h4",
        "properties": {
          "id": "global-config-file",
          "style": "position:relative;"
        },
        "children": [
          {
            "type": "element",
            "tagName": "a",
            "properties": {
              "href": "#global-config-file",
              "aria-label": "global config file permalink",
              "class": "header-link-class before"
            },
            "children": [
              {
                "type": "raw",
                "value": "<svg aria-hidden=\"true\" height=\"20\" version=\"1.1\" viewBox=\"0 0 16 16\" width=\"20\"><path fill-rule=\"evenodd\" d=\"M4 9h1v1H4c-1.5 0-3-1.69-3-3.5S2.55 3 4 3h4c1.45 0 3 1.69 3 3.5 0 1.41-.91 2.72-2 3.25V8.59c.58-.45 1-1.27 1-2.09C10 5.22 8.98 4 8 4H4c-.98 0-2 1.22-2 2.5S3 9 4 9zm9-3h-1v1h1c1 0 2 1.22 2 2.5S13.98 12 13 12H9c-.98 0-2-1.22-2-2.5 0-.83.42-1.64 1-2.09V6.25c-1.09.53-2 1.84-2 3.25C6 11.31 7.55 13 9 13h4c1.45 0 3-1.69 3-3.5S14.5 6 13 6z\"></path></svg>"
              }
            ]
          },
          {
            "type": "text",
            "value": "Global config file",
            "position": {
              "start": { "line": 76, "column": 6, "offset": 2110 },
              "end": { "line": 76, "column": 24, "offset": 2128 }
            }
          }
        ],
        "position": {
          "start": { "line": 76, "column": 1, "offset": 2105 },
          "end": { "line": 76, "column": 24, "offset": 2128 }
        }
      },
      { "type": "text", "value": "\n" },
      {
        "type": "element",
        "tagName": "p",
        "properties": {},
        "children": [
          {
            "type": "raw",
            "value": "<code class=\"language-text\">$PREFIX/etc/npmrc</code>",
            "position": {
              "start": { "line": 78, "column": 1, "offset": 2130 },
              "end": { "line": 78, "column": 20, "offset": 2149 }
            }
          },
          {
            "type": "text",
            "value": " (or the ",
            "position": {
              "start": { "line": 78, "column": 20, "offset": 2149 },
              "end": { "line": 78, "column": 29, "offset": 2158 }
            }
          },
          {
            "type": "raw",
            "value": "<code class=\"language-text\">globalconfig</code>",
            "position": {
              "start": { "line": 78, "column": 29, "offset": 2158 },
              "end": { "line": 78, "column": 43, "offset": 2172 }
            }
          },
          {
            "type": "text",
            "value": " param, if set above):\nThis file is an ini-file formatted list of ",
            "position": {
              "start": { "line": 78, "column": 43, "offset": 2172 },
              "end": { "line": 79, "column": 44, "offset": 2238 }
            }
          },
          {
            "type": "raw",
            "value": "<code class=\"language-text\">key = value</code>",
            "position": {
              "start": { "line": 79, "column": 44, "offset": 2238 },
              "end": { "line": 79, "column": 57, "offset": 2251 }
            }
          },
          {
            "type": "text",
            "value": " parameters.\nEnvironment variables can be replaced as above.",
            "position": {
              "start": { "line": 79, "column": 57, "offset": 2251 },
              "end": { "line": 80, "column": 48, "offset": 2311 }
            }
          }
        ],
        "position": {
          "start": { "line": 78, "column": 1, "offset": 2130 },
          "end": { "line": 80, "column": 48, "offset": 2311 }
        }
      },
      { "type": "text", "value": "\n" },
      {
        "type": "element",
        "tagName": "h4",
        "properties": {
          "id": "built-in-config-file",
          "style": "position:relative;"
        },
        "children": [
          {
            "type": "element",
            "tagName": "a",
            "properties": {
              "href": "#built-in-config-file",
              "aria-label": "built in config file permalink",
              "class": "header-link-class before"
            },
            "children": [
              {
                "type": "raw",
                "value": "<svg aria-hidden=\"true\" height=\"20\" version=\"1.1\" viewBox=\"0 0 16 16\" width=\"20\"><path fill-rule=\"evenodd\" d=\"M4 9h1v1H4c-1.5 0-3-1.69-3-3.5S2.55 3 4 3h4c1.45 0 3 1.69 3 3.5 0 1.41-.91 2.72-2 3.25V8.59c.58-.45 1-1.27 1-2.09C10 5.22 8.98 4 8 4H4c-.98 0-2 1.22-2 2.5S3 9 4 9zm9-3h-1v1h1c1 0 2 1.22 2 2.5S13.98 12 13 12H9c-.98 0-2-1.22-2-2.5 0-.83.42-1.64 1-2.09V6.25c-1.09.53-2 1.84-2 3.25C6 11.31 7.55 13 9 13h4c1.45 0 3-1.69 3-3.5S14.5 6 13 6z\"></path></svg>"
              }
            ]
          },
          {
            "type": "text",
            "value": "Built-in config file",
            "position": {
              "start": { "line": 82, "column": 6, "offset": 2318 },
              "end": { "line": 82, "column": 26, "offset": 2338 }
            }
          }
        ],
        "position": {
          "start": { "line": 82, "column": 1, "offset": 2313 },
          "end": { "line": 82, "column": 26, "offset": 2338 }
        }
      },
      { "type": "text", "value": "\n" },
      {
        "type": "element",
        "tagName": "p",
        "properties": {},
        "children": [
          {
            "type": "raw",
            "value": "<code class=\"language-text\">path/to/npm/itself/npmrc</code>",
            "position": {
              "start": { "line": 84, "column": 1, "offset": 2340 },
              "end": { "line": 84, "column": 27, "offset": 2366 }
            }
          }
        ],
        "position": {
          "start": { "line": 84, "column": 1, "offset": 2340 },
          "end": { "line": 84, "column": 27, "offset": 2366 }
        }
      },
      { "type": "text", "value": "\n" },
      {
        "type": "element",
        "tagName": "p",
        "properties": {},
        "children": [
          {
            "type": "text",
            "value": "This is an unchangeable \"builtin\" configuration file that npm keeps\nconsistent across updates. Set fields in here using the ",
            "position": {
              "start": { "line": 86, "column": 1, "offset": 2368 },
              "end": { "line": 87, "column": 57, "offset": 2492 }
            }
          },
          {
            "type": "raw",
            "value": "<code class=\"language-text\">./configure</code>",
            "position": {
              "start": { "line": 87, "column": 57, "offset": 2492 },
              "end": { "line": 87, "column": 70, "offset": 2505 }
            }
          },
          {
            "type": "text",
            "value": "\nscript that comes with npm. This is primarily for distribution\nmaintainers to override default configs in a standard and consistent\nmanner.",
            "position": {
              "start": { "line": 87, "column": 70, "offset": 2505 },
              "end": { "line": 90, "column": 8, "offset": 2645 }
            }
          }
        ],
        "position": {
          "start": { "line": 86, "column": 1, "offset": 2368 },
          "end": { "line": 90, "column": 8, "offset": 2645 }
        }
      },
      { "type": "text", "value": "\n" },
      {
        "type": "element",
        "tagName": "h3",
        "properties": { "id": "see-also", "style": "position:relative;" },
        "children": [
          {
            "type": "element",
            "tagName": "a",
            "properties": {
              "href": "#see-also",
              "aria-label": "see also permalink",
              "class": "header-link-class before"
            },
            "children": [
              {
                "type": "raw",
                "value": "<svg aria-hidden=\"true\" height=\"20\" version=\"1.1\" viewBox=\"0 0 16 16\" width=\"20\"><path fill-rule=\"evenodd\" d=\"M4 9h1v1H4c-1.5 0-3-1.69-3-3.5S2.55 3 4 3h4c1.45 0 3 1.69 3 3.5 0 1.41-.91 2.72-2 3.25V8.59c.58-.45 1-1.27 1-2.09C10 5.22 8.98 4 8 4H4c-.98 0-2 1.22-2 2.5S3 9 4 9zm9-3h-1v1h1c1 0 2 1.22 2 2.5S13.98 12 13 12H9c-.98 0-2-1.22-2-2.5 0-.83.42-1.64 1-2.09V6.25c-1.09.53-2 1.84-2 3.25C6 11.31 7.55 13 9 13h4c1.45 0 3-1.69 3-3.5S14.5 6 13 6z\"></path></svg>"
              }
            ]
          },
          {
            "type": "text",
            "value": "See also",
            "position": {
              "start": { "line": 92, "column": 5, "offset": 2651 },
              "end": { "line": 92, "column": 13, "offset": 2659 }
            }
          }
        ],
        "position": {
          "start": { "line": 92, "column": 1, "offset": 2647 },
          "end": { "line": 92, "column": 13, "offset": 2659 }
        }
      },
      { "type": "text", "value": "\n" },
      {
        "type": "element",
        "tagName": "ul",
        "properties": {},
        "children": [
          { "type": "text", "value": "\n" },
          {
            "type": "element",
            "tagName": "li",
            "properties": {},
            "children": [
              {
                "type": "element",
                "tagName": "a",
                "properties": { "href": "/configuring-npm/folders" },
                "children": [
                  {
                    "type": "text",
                    "value": "npm folders",
                    "position": {
                      "start": { "line": 94, "column": 4, "offset": 2664 },
                      "end": { "line": 94, "column": 15, "offset": 2675 }
                    }
                  }
                ],
                "position": {
                  "start": { "line": 94, "column": 3, "offset": 2663 },
                  "end": { "line": 94, "column": 42, "offset": 2702 }
                }
              }
            ],
            "position": {
              "start": { "line": 94, "column": 1, "offset": 2661 },
              "end": { "line": 94, "column": 42, "offset": 2702 }
            }
          },
          { "type": "text", "value": "\n" },
          {
            "type": "element",
            "tagName": "li",
            "properties": {},
            "children": [
              {
                "type": "element",
                "tagName": "a",
                "properties": { "href": "/cli-commands/npm-config" },
                "children": [
                  {
                    "type": "text",
                    "value": "npm config",
                    "position": {
                      "start": { "line": 95, "column": 4, "offset": 2706 },
                      "end": { "line": 95, "column": 14, "offset": 2716 }
                    }
                  }
                ],
                "position": {
                  "start": { "line": 95, "column": 3, "offset": 2705 },
                  "end": { "line": 95, "column": 41, "offset": 2743 }
                }
              }
            ],
            "position": {
              "start": { "line": 95, "column": 1, "offset": 2703 },
              "end": { "line": 95, "column": 41, "offset": 2743 }
            }
          },
          { "type": "text", "value": "\n" },
          {
            "type": "element",
            "tagName": "li",
            "properties": {},
            "children": [
              {
                "type": "element",
                "tagName": "a",
                "properties": { "href": "/using-npm/config" },
                "children": [
                  {
                    "type": "text",
                    "value": "config",
                    "position": {
                      "start": { "line": 96, "column": 4, "offset": 2747 },
                      "end": { "line": 96, "column": 10, "offset": 2753 }
                    }
                  }
                ],
                "position": {
                  "start": { "line": 96, "column": 3, "offset": 2746 },
                  "end": { "line": 96, "column": 30, "offset": 2773 }
                }
              }
            ],
            "position": {
              "start": { "line": 96, "column": 1, "offset": 2744 },
              "end": { "line": 96, "column": 30, "offset": 2773 }
            }
          },
          { "type": "text", "value": "\n" },
          {
            "type": "element",
            "tagName": "li",
            "properties": {},
            "children": [
              {
                "type": "element",
                "tagName": "a",
                "properties": { "href": "/configuring-npm/package-json" },
                "children": [
                  {
                    "type": "text",
                    "value": "package.json",
                    "position": {
                      "start": { "line": 97, "column": 4, "offset": 2777 },
                      "end": { "line": 97, "column": 16, "offset": 2789 }
                    }
                  }
                ],
                "position": {
                  "start": { "line": 97, "column": 3, "offset": 2776 },
                  "end": { "line": 97, "column": 48, "offset": 2821 }
                }
              }
            ],
            "position": {
              "start": { "line": 97, "column": 1, "offset": 2774 },
              "end": { "line": 97, "column": 48, "offset": 2821 }
            }
          },
          { "type": "text", "value": "\n" },
          {
            "type": "element",
            "tagName": "li",
            "properties": {},
            "children": [
              {
                "type": "element",
                "tagName": "a",
                "properties": { "href": "/cli-commands/npm" },
                "children": [
                  {
                    "type": "text",
                    "value": "npm",
                    "position": {
                      "start": { "line": 98, "column": 4, "offset": 2825 },
                      "end": { "line": 98, "column": 7, "offset": 2828 }
                    }
                  }
                ],
                "position": {
                  "start": { "line": 98, "column": 3, "offset": 2824 },
                  "end": { "line": 98, "column": 27, "offset": 2848 }
                }
              }
            ],
            "position": {
              "start": { "line": 98, "column": 1, "offset": 2822 },
              "end": { "line": 98, "column": 27, "offset": 2848 }
            }
          },
          { "type": "text", "value": "\n" }
        ],
        "position": {
          "start": { "line": 94, "column": 1, "offset": 2661 },
          "end": { "line": 98, "column": 27, "offset": 2848 }
        }
      }
    ],
    "position": {
      "start": { "line": 1, "column": 1, "offset": 0 },
      "end": { "line": 99, "column": 1, "offset": 2849 }
    }
  }
}
