{
  "expireTime": 9007200887118514000,
  "key": "transformer-remark-markdown-html-ast-b691091a57d80504f91eb3302f6fcd5f-gatsby-remark-autolink-headersgatsby-remark-prismjs-",
  "val": {
    "type": "root",
    "children": [
      {
        "type": "element",
        "tagName": "h1",
        "properties": { "id": "registry7", "style": "position:relative;" },
        "children": [
          {
            "type": "element",
            "tagName": "a",
            "properties": {
              "href": "#registry7",
              "aria-label": "registry7 permalink",
              "class": "header-link-class before"
            },
            "children": [
              {
                "type": "raw",
                "value": "<svg aria-hidden=\"true\" height=\"20\" version=\"1.1\" viewBox=\"0 0 16 16\" width=\"20\"><path fill-rule=\"evenodd\" d=\"M4 9h1v1H4c-1.5 0-3-1.69-3-3.5S2.55 3 4 3h4c1.45 0 3 1.69 3 3.5 0 1.41-.91 2.72-2 3.25V8.59c.58-.45 1-1.27 1-2.09C10 5.22 8.98 4 8 4H4c-.98 0-2 1.22-2 2.5S3 9 4 9zm9-3h-1v1h1c1 0 2 1.22 2 2.5S13.98 12 13 12H9c-.98 0-2-1.22-2-2.5 0-.83.42-1.64 1-2.09V6.25c-1.09.53-2 1.84-2 3.25C6 11.31 7.55 13 9 13h4c1.45 0 3-1.69 3-3.5S14.5 6 13 6z\"></path></svg>"
              }
            ]
          },
          {
            "type": "text",
            "value": "registry(7)",
            "position": {
              "start": { "line": 2, "column": 3, "offset": 3 },
              "end": { "line": 2, "column": 14, "offset": 14 }
            }
          }
        ],
        "position": {
          "start": { "line": 2, "column": 1, "offset": 1 },
          "end": { "line": 2, "column": 14, "offset": 14 }
        }
      },
      { "type": "text", "value": "\n" },
      {
        "type": "element",
        "tagName": "h2",
        "properties": {
          "id": "the-javascript-package-registry",
          "style": "position:relative;"
        },
        "children": [
          {
            "type": "element",
            "tagName": "a",
            "properties": {
              "href": "#the-javascript-package-registry",
              "aria-label": "the javascript package registry permalink",
              "class": "header-link-class before"
            },
            "children": [
              {
                "type": "raw",
                "value": "<svg aria-hidden=\"true\" height=\"20\" version=\"1.1\" viewBox=\"0 0 16 16\" width=\"20\"><path fill-rule=\"evenodd\" d=\"M4 9h1v1H4c-1.5 0-3-1.69-3-3.5S2.55 3 4 3h4c1.45 0 3 1.69 3 3.5 0 1.41-.91 2.72-2 3.25V8.59c.58-.45 1-1.27 1-2.09C10 5.22 8.98 4 8 4H4c-.98 0-2 1.22-2 2.5S3 9 4 9zm9-3h-1v1h1c1 0 2 1.22 2 2.5S13.98 12 13 12H9c-.98 0-2-1.22-2-2.5 0-.83.42-1.64 1-2.09V6.25c-1.09.53-2 1.84-2 3.25C6 11.31 7.55 13 9 13h4c1.45 0 3-1.69 3-3.5S14.5 6 13 6z\"></path></svg>"
              }
            ]
          },
          {
            "type": "text",
            "value": "The JavaScript Package Registry",
            "position": {
              "start": { "line": 4, "column": 4, "offset": 19 },
              "end": { "line": 4, "column": 35, "offset": 50 }
            }
          }
        ],
        "position": {
          "start": { "line": 4, "column": 1, "offset": 16 },
          "end": { "line": 4, "column": 35, "offset": 50 }
        }
      },
      { "type": "text", "value": "\n" },
      {
        "type": "element",
        "tagName": "h3",
        "properties": { "id": "description", "style": "position:relative;" },
        "children": [
          {
            "type": "element",
            "tagName": "a",
            "properties": {
              "href": "#description",
              "aria-label": "description permalink",
              "class": "header-link-class before"
            },
            "children": [
              {
                "type": "raw",
                "value": "<svg aria-hidden=\"true\" height=\"20\" version=\"1.1\" viewBox=\"0 0 16 16\" width=\"20\"><path fill-rule=\"evenodd\" d=\"M4 9h1v1H4c-1.5 0-3-1.69-3-3.5S2.55 3 4 3h4c1.45 0 3 1.69 3 3.5 0 1.41-.91 2.72-2 3.25V8.59c.58-.45 1-1.27 1-2.09C10 5.22 8.98 4 8 4H4c-.98 0-2 1.22-2 2.5S3 9 4 9zm9-3h-1v1h1c1 0 2 1.22 2 2.5S13.98 12 13 12H9c-.98 0-2-1.22-2-2.5 0-.83.42-1.64 1-2.09V6.25c-1.09.53-2 1.84-2 3.25C6 11.31 7.55 13 9 13h4c1.45 0 3-1.69 3-3.5S14.5 6 13 6z\"></path></svg>"
              }
            ]
          },
          {
            "type": "text",
            "value": "Description",
            "position": {
              "start": { "line": 6, "column": 5, "offset": 56 },
              "end": { "line": 6, "column": 16, "offset": 67 }
            }
          }
        ],
        "position": {
          "start": { "line": 6, "column": 1, "offset": 52 },
          "end": { "line": 6, "column": 16, "offset": 67 }
        }
      },
      { "type": "text", "value": "\n" },
      {
        "type": "element",
        "tagName": "p",
        "properties": {},
        "children": [
          {
            "type": "text",
            "value": "To resolve packages by name and version, npm talks to a registry website\nthat implements the CommonJS Package Registry specification for reading\npackage info.",
            "position": {
              "start": { "line": 8, "column": 1, "offset": 69 },
              "end": { "line": 10, "column": 14, "offset": 227 }
            }
          }
        ],
        "position": {
          "start": { "line": 8, "column": 1, "offset": 69 },
          "end": { "line": 10, "column": 14, "offset": 227 }
        }
      },
      { "type": "text", "value": "\n" },
      {
        "type": "element",
        "tagName": "p",
        "properties": {},
        "children": [
          {
            "type": "text",
            "value": "npm is configured to use npm, Inc.'s public registry at\n",
            "position": {
              "start": { "line": 12, "column": 1, "offset": 229 },
              "end": { "line": 13, "column": 1, "offset": 285 }
            }
          },
          {
            "type": "element",
            "tagName": "a",
            "properties": { "href": "https://registry.npmjs.org" },
            "children": [
              {
                "type": "text",
                "value": "https://registry.npmjs.org",
                "position": {
                  "start": { "line": 13, "column": 2, "offset": 286 },
                  "end": { "line": 13, "column": 28, "offset": 312 }
                }
              }
            ],
            "position": {
              "start": { "line": 13, "column": 1, "offset": 285 },
              "end": { "line": 13, "column": 29, "offset": 313 }
            }
          },
          {
            "type": "text",
            "value": " by default. Use of the npm public registry is\nsubject to terms of use available at ",
            "position": {
              "start": { "line": 13, "column": 29, "offset": 313 },
              "end": { "line": 14, "column": 38, "offset": 397 }
            }
          },
          {
            "type": "element",
            "tagName": "a",
            "properties": { "href": "https://www.npmjs.com/policies/terms" },
            "children": [
              {
                "type": "text",
                "value": "https://www.npmjs.com/policies/terms",
                "position": {
                  "start": { "line": 14, "column": 39, "offset": 398 },
                  "end": { "line": 14, "column": 75, "offset": 434 }
                }
              }
            ],
            "position": {
              "start": { "line": 14, "column": 38, "offset": 397 },
              "end": { "line": 14, "column": 76, "offset": 435 }
            }
          },
          {
            "type": "text",
            "value": ".",
            "position": {
              "start": { "line": 14, "column": 76, "offset": 435 },
              "end": { "line": 14, "column": 77, "offset": 436 }
            }
          }
        ],
        "position": {
          "start": { "line": 12, "column": 1, "offset": 229 },
          "end": { "line": 14, "column": 77, "offset": 436 }
        }
      },
      { "type": "text", "value": "\n" },
      {
        "type": "element",
        "tagName": "p",
        "properties": {},
        "children": [
          {
            "type": "text",
            "value": "You can configure npm to use any compatible registry you like, and even run\nyour own registry. Use of someone else's registry may be governed by their\nterms of use.",
            "position": {
              "start": { "line": 16, "column": 1, "offset": 438 },
              "end": { "line": 18, "column": 14, "offset": 602 }
            }
          }
        ],
        "position": {
          "start": { "line": 16, "column": 1, "offset": 438 },
          "end": { "line": 18, "column": 14, "offset": 602 }
        }
      },
      { "type": "text", "value": "\n" },
      {
        "type": "element",
        "tagName": "p",
        "properties": {},
        "children": [
          {
            "type": "text",
            "value": "npm's package registry implementation supports several\nwrite APIs as well, to allow for publishing packages and managing user\naccount information.",
            "position": {
              "start": { "line": 20, "column": 1, "offset": 604 },
              "end": { "line": 22, "column": 21, "offset": 750 }
            }
          }
        ],
        "position": {
          "start": { "line": 20, "column": 1, "offset": 604 },
          "end": { "line": 22, "column": 21, "offset": 750 }
        }
      },
      { "type": "text", "value": "\n" },
      {
        "type": "element",
        "tagName": "p",
        "properties": {},
        "children": [
          {
            "type": "text",
            "value": "The npm public registry is powered by a CouchDB database,\nof which there is a public mirror at\n",
            "position": {
              "start": { "line": 24, "column": 1, "offset": 752 },
              "end": { "line": 26, "column": 1, "offset": 847 }
            }
          },
          {
            "type": "element",
            "tagName": "a",
            "properties": { "href": "https://skimdb.npmjs.com/registry" },
            "children": [
              {
                "type": "text",
                "value": "https://skimdb.npmjs.com/registry",
                "position": {
                  "start": { "line": 26, "column": 2, "offset": 848 },
                  "end": { "line": 26, "column": 35, "offset": 881 }
                }
              }
            ],
            "position": {
              "start": { "line": 26, "column": 1, "offset": 847 },
              "end": { "line": 26, "column": 36, "offset": 882 }
            }
          },
          {
            "type": "text",
            "value": ". The code for the couchapp is\navailable at ",
            "position": {
              "start": { "line": 26, "column": 36, "offset": 882 },
              "end": { "line": 27, "column": 14, "offset": 926 }
            }
          },
          {
            "type": "element",
            "tagName": "a",
            "properties": {
              "href": "https://github.com/npm/npm-registry-couchapp"
            },
            "children": [
              {
                "type": "text",
                "value": "https://github.com/npm/npm-registry-couchapp",
                "position": {
                  "start": { "line": 27, "column": 15, "offset": 927 },
                  "end": { "line": 27, "column": 59, "offset": 971 }
                }
              }
            ],
            "position": {
              "start": { "line": 27, "column": 14, "offset": 926 },
              "end": { "line": 27, "column": 60, "offset": 972 }
            }
          },
          {
            "type": "text",
            "value": ".",
            "position": {
              "start": { "line": 27, "column": 60, "offset": 972 },
              "end": { "line": 27, "column": 61, "offset": 973 }
            }
          }
        ],
        "position": {
          "start": { "line": 24, "column": 1, "offset": 752 },
          "end": { "line": 27, "column": 61, "offset": 973 }
        }
      },
      { "type": "text", "value": "\n" },
      {
        "type": "element",
        "tagName": "p",
        "properties": {},
        "children": [
          {
            "type": "text",
            "value": "The registry URL used is determined by the scope of the package (see\n",
            "position": {
              "start": { "line": 29, "column": 1, "offset": 975 },
              "end": { "line": 30, "column": 1, "offset": 1044 }
            }
          },
          {
            "type": "element",
            "tagName": "a",
            "properties": { "href": "/using-npm/scope" },
            "children": [
              {
                "type": "raw",
                "value": "<code class=\"language-text\">scope</code>",
                "position": {
                  "start": { "line": 30, "column": 2, "offset": 1045 },
                  "end": { "line": 30, "column": 9, "offset": 1052 }
                }
              }
            ],
            "position": {
              "start": { "line": 30, "column": 1, "offset": 1044 },
              "end": { "line": 30, "column": 28, "offset": 1071 }
            }
          },
          {
            "type": "text",
            "value": ". If no scope is specified, the default registry is used, which is\nsupplied by the ",
            "position": {
              "start": { "line": 30, "column": 28, "offset": 1071 },
              "end": { "line": 31, "column": 17, "offset": 1154 }
            }
          },
          {
            "type": "raw",
            "value": "<code class=\"language-text\">registry</code>",
            "position": {
              "start": { "line": 31, "column": 17, "offset": 1154 },
              "end": { "line": 31, "column": 27, "offset": 1164 }
            }
          },
          {
            "type": "text",
            "value": " config parameter. See ",
            "position": {
              "start": { "line": 31, "column": 27, "offset": 1164 },
              "end": { "line": 31, "column": 50, "offset": 1187 }
            }
          },
          {
            "type": "element",
            "tagName": "a",
            "properties": { "href": "/cli-commands/npm-config" },
            "children": [
              {
                "type": "raw",
                "value": "<code class=\"language-text\">npm config</code>",
                "position": {
                  "start": { "line": 31, "column": 51, "offset": 1188 },
                  "end": { "line": 31, "column": 63, "offset": 1200 }
                }
              }
            ],
            "position": {
              "start": { "line": 31, "column": 50, "offset": 1187 },
              "end": { "line": 31, "column": 90, "offset": 1227 }
            }
          },
          {
            "type": "text",
            "value": ",\n",
            "position": {
              "start": { "line": 31, "column": 90, "offset": 1227 },
              "end": { "line": 32, "column": 1, "offset": 1229 }
            }
          },
          {
            "type": "element",
            "tagName": "a",
            "properties": { "href": "/configuring-npm/npmrc" },
            "children": [
              {
                "type": "raw",
                "value": "<code class=\"language-text\">npmrc</code>",
                "position": {
                  "start": { "line": 32, "column": 2, "offset": 1230 },
                  "end": { "line": 32, "column": 9, "offset": 1237 }
                }
              }
            ],
            "position": {
              "start": { "line": 32, "column": 1, "offset": 1229 },
              "end": { "line": 32, "column": 34, "offset": 1262 }
            }
          },
          {
            "type": "text",
            "value": ", and ",
            "position": {
              "start": { "line": 32, "column": 34, "offset": 1262 },
              "end": { "line": 32, "column": 40, "offset": 1268 }
            }
          },
          {
            "type": "element",
            "tagName": "a",
            "properties": { "href": "/using-npm/config" },
            "children": [
              {
                "type": "raw",
                "value": "<code class=\"language-text\">config</code>",
                "position": {
                  "start": { "line": 32, "column": 41, "offset": 1269 },
                  "end": { "line": 32, "column": 49, "offset": 1277 }
                }
              }
            ],
            "position": {
              "start": { "line": 32, "column": 40, "offset": 1268 },
              "end": { "line": 32, "column": 69, "offset": 1297 }
            }
          },
          {
            "type": "text",
            "value": " for more on managing npm's configuration.",
            "position": {
              "start": { "line": 32, "column": 69, "offset": 1297 },
              "end": { "line": 32, "column": 111, "offset": 1339 }
            }
          }
        ],
        "position": {
          "start": { "line": 29, "column": 1, "offset": 975 },
          "end": { "line": 32, "column": 111, "offset": 1339 }
        }
      },
      { "type": "text", "value": "\n" },
      {
        "type": "element",
        "tagName": "h3",
        "properties": {
          "id": "does-npm-send-any-information-about-me-back-to-the-registry",
          "style": "position:relative;"
        },
        "children": [
          {
            "type": "element",
            "tagName": "a",
            "properties": {
              "href": "#does-npm-send-any-information-about-me-back-to-the-registry",
              "aria-label": "does npm send any information about me back to the registry permalink",
              "class": "header-link-class before"
            },
            "children": [
              {
                "type": "raw",
                "value": "<svg aria-hidden=\"true\" height=\"20\" version=\"1.1\" viewBox=\"0 0 16 16\" width=\"20\"><path fill-rule=\"evenodd\" d=\"M4 9h1v1H4c-1.5 0-3-1.69-3-3.5S2.55 3 4 3h4c1.45 0 3 1.69 3 3.5 0 1.41-.91 2.72-2 3.25V8.59c.58-.45 1-1.27 1-2.09C10 5.22 8.98 4 8 4H4c-.98 0-2 1.22-2 2.5S3 9 4 9zm9-3h-1v1h1c1 0 2 1.22 2 2.5S13.98 12 13 12H9c-.98 0-2-1.22-2-2.5 0-.83.42-1.64 1-2.09V6.25c-1.09.53-2 1.84-2 3.25C6 11.31 7.55 13 9 13h4c1.45 0 3-1.69 3-3.5S14.5 6 13 6z\"></path></svg>"
              }
            ]
          },
          {
            "type": "text",
            "value": "Does npm send any information about me back to the registry?",
            "position": {
              "start": { "line": 34, "column": 5, "offset": 1345 },
              "end": { "line": 34, "column": 65, "offset": 1405 }
            }
          }
        ],
        "position": {
          "start": { "line": 34, "column": 1, "offset": 1341 },
          "end": { "line": 34, "column": 65, "offset": 1405 }
        }
      },
      { "type": "text", "value": "\n" },
      {
        "type": "element",
        "tagName": "p",
        "properties": {},
        "children": [
          {
            "type": "text",
            "value": "Yes.",
            "position": {
              "start": { "line": 36, "column": 1, "offset": 1407 },
              "end": { "line": 36, "column": 5, "offset": 1411 }
            }
          }
        ],
        "position": {
          "start": { "line": 36, "column": 1, "offset": 1407 },
          "end": { "line": 36, "column": 5, "offset": 1411 }
        }
      },
      { "type": "text", "value": "\n" },
      {
        "type": "element",
        "tagName": "p",
        "properties": {},
        "children": [
          {
            "type": "text",
            "value": "When making requests of the registry npm adds two headers with information\nabout your environment:",
            "position": {
              "start": { "line": 38, "column": 1, "offset": 1413 },
              "end": { "line": 39, "column": 24, "offset": 1511 }
            }
          }
        ],
        "position": {
          "start": { "line": 38, "column": 1, "offset": 1413 },
          "end": { "line": 39, "column": 24, "offset": 1511 }
        }
      },
      { "type": "text", "value": "\n" },
      {
        "type": "element",
        "tagName": "ul",
        "properties": {},
        "children": [
          { "type": "text", "value": "\n" },
          {
            "type": "element",
            "tagName": "li",
            "properties": {},
            "children": [
              {
                "type": "raw",
                "value": "<code class=\"language-text\">Npm-Scope</code>",
                "position": {
                  "start": { "line": 41, "column": 3, "offset": 1515 },
                  "end": { "line": 41, "column": 14, "offset": 1526 }
                }
              },
              {
                "type": "text",
                "value": " – If your project is scoped, this header will contain its\nscope. In the future npm hopes to build registry features that use this\ninformation to allow you to customize your experience for your\norganization.",
                "position": {
                  "start": { "line": 41, "column": 14, "offset": 1526 },
                  "end": { "line": 44, "column": 16, "offset": 1739 }
                }
              }
            ],
            "position": {
              "start": { "line": 41, "column": 1, "offset": 1513 },
              "end": { "line": 44, "column": 16, "offset": 1739 }
            }
          },
          { "type": "text", "value": "\n" },
          {
            "type": "element",
            "tagName": "li",
            "properties": {},
            "children": [
              {
                "type": "raw",
                "value": "<code class=\"language-text\">Npm-In-CI</code>",
                "position": {
                  "start": { "line": 45, "column": 3, "offset": 1742 },
                  "end": { "line": 45, "column": 14, "offset": 1753 }
                }
              },
              {
                "type": "text",
                "value": " – Set to \"true\" if npm believes this install is running in a\ncontinuous integration environment, \"false\" otherwise. This is detected by\nlooking for the following environment variables: ",
                "position": {
                  "start": { "line": 45, "column": 14, "offset": 1753 },
                  "end": { "line": 47, "column": 52, "offset": 1943 }
                }
              },
              {
                "type": "raw",
                "value": "<code class=\"language-text\">CI</code>",
                "position": {
                  "start": { "line": 47, "column": 52, "offset": 1943 },
                  "end": { "line": 47, "column": 56, "offset": 1947 }
                }
              },
              {
                "type": "text",
                "value": ", ",
                "position": {
                  "start": { "line": 47, "column": 56, "offset": 1947 },
                  "end": { "line": 47, "column": 58, "offset": 1949 }
                }
              },
              {
                "type": "raw",
                "value": "<code class=\"language-text\">TDDIUM</code>",
                "position": {
                  "start": { "line": 47, "column": 58, "offset": 1949 },
                  "end": { "line": 47, "column": 66, "offset": 1957 }
                }
              },
              {
                "type": "text",
                "value": ",\n",
                "position": {
                  "start": { "line": 47, "column": 66, "offset": 1957 },
                  "end": { "line": 48, "column": 3, "offset": 1961 }
                }
              },
              {
                "type": "raw",
                "value": "<code class=\"language-text\">JENKINS_URL</code>",
                "position": {
                  "start": { "line": 48, "column": 3, "offset": 1961 },
                  "end": { "line": 48, "column": 16, "offset": 1974 }
                }
              },
              {
                "type": "text",
                "value": ", ",
                "position": {
                  "start": { "line": 48, "column": 16, "offset": 1974 },
                  "end": { "line": 48, "column": 18, "offset": 1976 }
                }
              },
              {
                "type": "raw",
                "value": "<code class=\"language-text\">bamboo.buildKey</code>",
                "position": {
                  "start": { "line": 48, "column": 18, "offset": 1976 },
                  "end": { "line": 48, "column": 35, "offset": 1993 }
                }
              },
              {
                "type": "text",
                "value": ". If you'd like to learn more you may find\nthe ",
                "position": {
                  "start": { "line": 48, "column": 35, "offset": 1993 },
                  "end": { "line": 49, "column": 7, "offset": 2042 }
                }
              },
              {
                "type": "element",
                "tagName": "a",
                "properties": {
                  "href": "https://github.com/npm/npm-registry-client/pull/129"
                },
                "children": [
                  {
                    "type": "text",
                    "value": "original PR",
                    "position": {
                      "start": { "line": 49, "column": 8, "offset": 2043 },
                      "end": { "line": 49, "column": 19, "offset": 2054 }
                    }
                  }
                ],
                "position": {
                  "start": { "line": 49, "column": 7, "offset": 2042 },
                  "end": { "line": 49, "column": 73, "offset": 2108 }
                }
              },
              {
                "type": "text",
                "value": "\ninteresting.\nThis is used to gather better metrics on how npm is used by humans, versus\nbuild farms.",
                "position": {
                  "start": { "line": 49, "column": 73, "offset": 2108 },
                  "end": { "line": 52, "column": 15, "offset": 2215 }
                }
              }
            ],
            "position": {
              "start": { "line": 45, "column": 1, "offset": 1740 },
              "end": { "line": 52, "column": 15, "offset": 2215 }
            }
          },
          { "type": "text", "value": "\n" }
        ],
        "position": {
          "start": { "line": 41, "column": 1, "offset": 1513 },
          "end": { "line": 52, "column": 15, "offset": 2215 }
        }
      },
      { "type": "text", "value": "\n" },
      {
        "type": "element",
        "tagName": "p",
        "properties": {},
        "children": [
          {
            "type": "text",
            "value": "The npm registry does not try to correlate the information in these headers\nwith any authenticated accounts that may be used in the same requests.",
            "position": {
              "start": { "line": 54, "column": 1, "offset": 2217 },
              "end": { "line": 55, "column": 71, "offset": 2363 }
            }
          }
        ],
        "position": {
          "start": { "line": 54, "column": 1, "offset": 2217 },
          "end": { "line": 55, "column": 71, "offset": 2363 }
        }
      },
      { "type": "text", "value": "\n" },
      {
        "type": "element",
        "tagName": "h3",
        "properties": {
          "id": "can-i-run-my-own-private-registry",
          "style": "position:relative;"
        },
        "children": [
          {
            "type": "element",
            "tagName": "a",
            "properties": {
              "href": "#can-i-run-my-own-private-registry",
              "aria-label": "can i run my own private registry permalink",
              "class": "header-link-class before"
            },
            "children": [
              {
                "type": "raw",
                "value": "<svg aria-hidden=\"true\" height=\"20\" version=\"1.1\" viewBox=\"0 0 16 16\" width=\"20\"><path fill-rule=\"evenodd\" d=\"M4 9h1v1H4c-1.5 0-3-1.69-3-3.5S2.55 3 4 3h4c1.45 0 3 1.69 3 3.5 0 1.41-.91 2.72-2 3.25V8.59c.58-.45 1-1.27 1-2.09C10 5.22 8.98 4 8 4H4c-.98 0-2 1.22-2 2.5S3 9 4 9zm9-3h-1v1h1c1 0 2 1.22 2 2.5S13.98 12 13 12H9c-.98 0-2-1.22-2-2.5 0-.83.42-1.64 1-2.09V6.25c-1.09.53-2 1.84-2 3.25C6 11.31 7.55 13 9 13h4c1.45 0 3-1.69 3-3.5S14.5 6 13 6z\"></path></svg>"
              }
            ]
          },
          {
            "type": "text",
            "value": "Can I run my own private registry?",
            "position": {
              "start": { "line": 57, "column": 5, "offset": 2369 },
              "end": { "line": 57, "column": 39, "offset": 2403 }
            }
          }
        ],
        "position": {
          "start": { "line": 57, "column": 1, "offset": 2365 },
          "end": { "line": 57, "column": 39, "offset": 2403 }
        }
      },
      { "type": "text", "value": "\n" },
      {
        "type": "element",
        "tagName": "p",
        "properties": {},
        "children": [
          {
            "type": "text",
            "value": "Yes!",
            "position": {
              "start": { "line": 59, "column": 1, "offset": 2405 },
              "end": { "line": 59, "column": 5, "offset": 2409 }
            }
          }
        ],
        "position": {
          "start": { "line": 59, "column": 1, "offset": 2405 },
          "end": { "line": 59, "column": 5, "offset": 2409 }
        }
      },
      { "type": "text", "value": "\n" },
      {
        "type": "element",
        "tagName": "p",
        "properties": {},
        "children": [
          {
            "type": "text",
            "value": "The easiest way is to replicate the couch database, and use the same (or\nsimilar) design doc to implement the APIs.",
            "position": {
              "start": { "line": 61, "column": 1, "offset": 2411 },
              "end": { "line": 62, "column": 43, "offset": 2526 }
            }
          }
        ],
        "position": {
          "start": { "line": 61, "column": 1, "offset": 2411 },
          "end": { "line": 62, "column": 43, "offset": 2526 }
        }
      },
      { "type": "text", "value": "\n" },
      {
        "type": "element",
        "tagName": "p",
        "properties": {},
        "children": [
          {
            "type": "text",
            "value": "If you set up continuous replication from the official CouchDB, and then\nset your internal CouchDB as the registry config, then you'll be able\nto read any published packages, in addition to your private ones, and by\ndefault will only publish internally.",
            "position": {
              "start": { "line": 64, "column": 1, "offset": 2528 },
              "end": { "line": 67, "column": 38, "offset": 2781 }
            }
          }
        ],
        "position": {
          "start": { "line": 64, "column": 1, "offset": 2528 },
          "end": { "line": 67, "column": 38, "offset": 2781 }
        }
      },
      { "type": "text", "value": "\n" },
      {
        "type": "element",
        "tagName": "p",
        "properties": {},
        "children": [
          {
            "type": "text",
            "value": "If you then want to publish a package for the whole world to see, you can\nsimply override the ",
            "position": {
              "start": { "line": 69, "column": 1, "offset": 2783 },
              "end": { "line": 70, "column": 21, "offset": 2877 }
            }
          },
          {
            "type": "raw",
            "value": "<code class=\"language-text\">--registry</code>",
            "position": {
              "start": { "line": 70, "column": 21, "offset": 2877 },
              "end": { "line": 70, "column": 33, "offset": 2889 }
            }
          },
          {
            "type": "text",
            "value": " option for that ",
            "position": {
              "start": { "line": 70, "column": 33, "offset": 2889 },
              "end": { "line": 70, "column": 50, "offset": 2906 }
            }
          },
          {
            "type": "raw",
            "value": "<code class=\"language-text\">publish</code>",
            "position": {
              "start": { "line": 70, "column": 50, "offset": 2906 },
              "end": { "line": 70, "column": 59, "offset": 2915 }
            }
          },
          {
            "type": "text",
            "value": " command.",
            "position": {
              "start": { "line": 70, "column": 59, "offset": 2915 },
              "end": { "line": 70, "column": 68, "offset": 2924 }
            }
          }
        ],
        "position": {
          "start": { "line": 69, "column": 1, "offset": 2783 },
          "end": { "line": 70, "column": 68, "offset": 2924 }
        }
      },
      { "type": "text", "value": "\n" },
      {
        "type": "element",
        "tagName": "h3",
        "properties": {
          "id": "i-dont-want-my-package-published-in-the-official-registry-its-private",
          "style": "position:relative;"
        },
        "children": [
          {
            "type": "element",
            "tagName": "a",
            "properties": {
              "href": "#i-dont-want-my-package-published-in-the-official-registry-its-private",
              "aria-label": "i dont want my package published in the official registry its private permalink",
              "class": "header-link-class before"
            },
            "children": [
              {
                "type": "raw",
                "value": "<svg aria-hidden=\"true\" height=\"20\" version=\"1.1\" viewBox=\"0 0 16 16\" width=\"20\"><path fill-rule=\"evenodd\" d=\"M4 9h1v1H4c-1.5 0-3-1.69-3-3.5S2.55 3 4 3h4c1.45 0 3 1.69 3 3.5 0 1.41-.91 2.72-2 3.25V8.59c.58-.45 1-1.27 1-2.09C10 5.22 8.98 4 8 4H4c-.98 0-2 1.22-2 2.5S3 9 4 9zm9-3h-1v1h1c1 0 2 1.22 2 2.5S13.98 12 13 12H9c-.98 0-2-1.22-2-2.5 0-.83.42-1.64 1-2.09V6.25c-1.09.53-2 1.84-2 3.25C6 11.31 7.55 13 9 13h4c1.45 0 3-1.69 3-3.5S14.5 6 13 6z\"></path></svg>"
              }
            ]
          },
          {
            "type": "text",
            "value": "I don't want my package published in the official registry. It's private.",
            "position": {
              "start": { "line": 72, "column": 5, "offset": 2930 },
              "end": { "line": 72, "column": 78, "offset": 3003 }
            }
          }
        ],
        "position": {
          "start": { "line": 72, "column": 1, "offset": 2926 },
          "end": { "line": 72, "column": 78, "offset": 3003 }
        }
      },
      { "type": "text", "value": "\n" },
      {
        "type": "element",
        "tagName": "p",
        "properties": {},
        "children": [
          {
            "type": "text",
            "value": "Set ",
            "position": {
              "start": { "line": 74, "column": 1, "offset": 3005 },
              "end": { "line": 74, "column": 5, "offset": 3009 }
            }
          },
          {
            "type": "raw",
            "value": "<code class=\"language-text\">&quot;private&quot;: true</code>",
            "position": {
              "start": { "line": 74, "column": 5, "offset": 3009 },
              "end": { "line": 74, "column": 22, "offset": 3026 }
            }
          },
          {
            "type": "text",
            "value": " in your package.json to prevent it from being\npublished at all, or\n",
            "position": {
              "start": { "line": 74, "column": 22, "offset": 3026 },
              "end": { "line": 76, "column": 1, "offset": 3094 }
            }
          },
          {
            "type": "raw",
            "value": "<code class=\"language-text\">&quot;publishConfig&quot;:{&quot;registry&quot;:&quot;http://my-internal-registry.local&quot;}</code>",
            "position": {
              "start": { "line": 76, "column": 1, "offset": 3094 },
              "end": { "line": 76, "column": 67, "offset": 3160 }
            }
          },
          {
            "type": "text",
            "value": "\nto force it to be published only to your internal registry.",
            "position": {
              "start": { "line": 76, "column": 67, "offset": 3160 },
              "end": { "line": 77, "column": 60, "offset": 3220 }
            }
          }
        ],
        "position": {
          "start": { "line": 74, "column": 1, "offset": 3005 },
          "end": { "line": 77, "column": 60, "offset": 3220 }
        }
      },
      { "type": "text", "value": "\n" },
      {
        "type": "element",
        "tagName": "p",
        "properties": {},
        "children": [
          {
            "type": "text",
            "value": "See ",
            "position": {
              "start": { "line": 79, "column": 1, "offset": 3222 },
              "end": { "line": 79, "column": 5, "offset": 3226 }
            }
          },
          {
            "type": "element",
            "tagName": "a",
            "properties": { "href": "/configuring-npm/package-json" },
            "children": [
              {
                "type": "raw",
                "value": "<code class=\"language-text\">package.json</code>",
                "position": {
                  "start": { "line": 79, "column": 6, "offset": 3227 },
                  "end": { "line": 79, "column": 20, "offset": 3241 }
                }
              }
            ],
            "position": {
              "start": { "line": 79, "column": 5, "offset": 3226 },
              "end": { "line": 79, "column": 52, "offset": 3273 }
            }
          },
          {
            "type": "text",
            "value": " for more info on what goes in the package.json file.",
            "position": {
              "start": { "line": 79, "column": 52, "offset": 3273 },
              "end": { "line": 79, "column": 105, "offset": 3326 }
            }
          }
        ],
        "position": {
          "start": { "line": 79, "column": 1, "offset": 3222 },
          "end": { "line": 79, "column": 105, "offset": 3326 }
        }
      },
      { "type": "text", "value": "\n" },
      {
        "type": "element",
        "tagName": "h3",
        "properties": {
          "id": "will-you-replicate-from-my-registry-into-the-public-one",
          "style": "position:relative;"
        },
        "children": [
          {
            "type": "element",
            "tagName": "a",
            "properties": {
              "href": "#will-you-replicate-from-my-registry-into-the-public-one",
              "aria-label": "will you replicate from my registry into the public one permalink",
              "class": "header-link-class before"
            },
            "children": [
              {
                "type": "raw",
                "value": "<svg aria-hidden=\"true\" height=\"20\" version=\"1.1\" viewBox=\"0 0 16 16\" width=\"20\"><path fill-rule=\"evenodd\" d=\"M4 9h1v1H4c-1.5 0-3-1.69-3-3.5S2.55 3 4 3h4c1.45 0 3 1.69 3 3.5 0 1.41-.91 2.72-2 3.25V8.59c.58-.45 1-1.27 1-2.09C10 5.22 8.98 4 8 4H4c-.98 0-2 1.22-2 2.5S3 9 4 9zm9-3h-1v1h1c1 0 2 1.22 2 2.5S13.98 12 13 12H9c-.98 0-2-1.22-2-2.5 0-.83.42-1.64 1-2.09V6.25c-1.09.53-2 1.84-2 3.25C6 11.31 7.55 13 9 13h4c1.45 0 3-1.69 3-3.5S14.5 6 13 6z\"></path></svg>"
              }
            ]
          },
          {
            "type": "text",
            "value": "Will you replicate from my registry into the public one?",
            "position": {
              "start": { "line": 81, "column": 5, "offset": 3332 },
              "end": { "line": 81, "column": 61, "offset": 3388 }
            }
          }
        ],
        "position": {
          "start": { "line": 81, "column": 1, "offset": 3328 },
          "end": { "line": 81, "column": 61, "offset": 3388 }
        }
      },
      { "type": "text", "value": "\n" },
      {
        "type": "element",
        "tagName": "p",
        "properties": {},
        "children": [
          {
            "type": "text",
            "value": "No. If you want things to be public, then publish them into the public\nregistry using npm. What little security there is would be for nought\notherwise.",
            "position": {
              "start": { "line": 83, "column": 1, "offset": 3390 },
              "end": { "line": 85, "column": 11, "offset": 3541 }
            }
          }
        ],
        "position": {
          "start": { "line": 83, "column": 1, "offset": 3390 },
          "end": { "line": 85, "column": 11, "offset": 3541 }
        }
      },
      { "type": "text", "value": "\n" },
      {
        "type": "element",
        "tagName": "h3",
        "properties": {
          "id": "do-i-have-to-use-couchdb-to-build-a-registry-that-npm-can-talk-to",
          "style": "position:relative;"
        },
        "children": [
          {
            "type": "element",
            "tagName": "a",
            "properties": {
              "href": "#do-i-have-to-use-couchdb-to-build-a-registry-that-npm-can-talk-to",
              "aria-label": "do i have to use couchdb to build a registry that npm can talk to permalink",
              "class": "header-link-class before"
            },
            "children": [
              {
                "type": "raw",
                "value": "<svg aria-hidden=\"true\" height=\"20\" version=\"1.1\" viewBox=\"0 0 16 16\" width=\"20\"><path fill-rule=\"evenodd\" d=\"M4 9h1v1H4c-1.5 0-3-1.69-3-3.5S2.55 3 4 3h4c1.45 0 3 1.69 3 3.5 0 1.41-.91 2.72-2 3.25V8.59c.58-.45 1-1.27 1-2.09C10 5.22 8.98 4 8 4H4c-.98 0-2 1.22-2 2.5S3 9 4 9zm9-3h-1v1h1c1 0 2 1.22 2 2.5S13.98 12 13 12H9c-.98 0-2-1.22-2-2.5 0-.83.42-1.64 1-2.09V6.25c-1.09.53-2 1.84-2 3.25C6 11.31 7.55 13 9 13h4c1.45 0 3-1.69 3-3.5S14.5 6 13 6z\"></path></svg>"
              }
            ]
          },
          {
            "type": "text",
            "value": "Do I have to use couchdb to build a registry that npm can talk to?",
            "position": {
              "start": { "line": 87, "column": 5, "offset": 3547 },
              "end": { "line": 87, "column": 71, "offset": 3613 }
            }
          }
        ],
        "position": {
          "start": { "line": 87, "column": 1, "offset": 3543 },
          "end": { "line": 87, "column": 71, "offset": 3613 }
        }
      },
      { "type": "text", "value": "\n" },
      {
        "type": "element",
        "tagName": "p",
        "properties": {},
        "children": [
          {
            "type": "text",
            "value": "No, but it's way easier. Basically, yes, you do, or you have to\neffectively implement the entire CouchDB API anyway.",
            "position": {
              "start": { "line": 89, "column": 1, "offset": 3615 },
              "end": { "line": 90, "column": 53, "offset": 3731 }
            }
          }
        ],
        "position": {
          "start": { "line": 89, "column": 1, "offset": 3615 },
          "end": { "line": 90, "column": 53, "offset": 3731 }
        }
      },
      { "type": "text", "value": "\n" },
      {
        "type": "element",
        "tagName": "h3",
        "properties": {
          "id": "is-there-a-website-or-something-to-see-package-docs-and-such",
          "style": "position:relative;"
        },
        "children": [
          {
            "type": "element",
            "tagName": "a",
            "properties": {
              "href": "#is-there-a-website-or-something-to-see-package-docs-and-such",
              "aria-label": "is there a website or something to see package docs and such permalink",
              "class": "header-link-class before"
            },
            "children": [
              {
                "type": "raw",
                "value": "<svg aria-hidden=\"true\" height=\"20\" version=\"1.1\" viewBox=\"0 0 16 16\" width=\"20\"><path fill-rule=\"evenodd\" d=\"M4 9h1v1H4c-1.5 0-3-1.69-3-3.5S2.55 3 4 3h4c1.45 0 3 1.69 3 3.5 0 1.41-.91 2.72-2 3.25V8.59c.58-.45 1-1.27 1-2.09C10 5.22 8.98 4 8 4H4c-.98 0-2 1.22-2 2.5S3 9 4 9zm9-3h-1v1h1c1 0 2 1.22 2 2.5S13.98 12 13 12H9c-.98 0-2-1.22-2-2.5 0-.83.42-1.64 1-2.09V6.25c-1.09.53-2 1.84-2 3.25C6 11.31 7.55 13 9 13h4c1.45 0 3-1.69 3-3.5S14.5 6 13 6z\"></path></svg>"
              }
            ]
          },
          {
            "type": "text",
            "value": "Is there a website or something to see package docs and such?",
            "position": {
              "start": { "line": 92, "column": 5, "offset": 3737 },
              "end": { "line": 92, "column": 66, "offset": 3798 }
            }
          }
        ],
        "position": {
          "start": { "line": 92, "column": 1, "offset": 3733 },
          "end": { "line": 92, "column": 66, "offset": 3798 }
        }
      },
      { "type": "text", "value": "\n" },
      {
        "type": "element",
        "tagName": "p",
        "properties": {},
        "children": [
          {
            "type": "text",
            "value": "Yes, head over to ",
            "position": {
              "start": { "line": 94, "column": 1, "offset": 3800 },
              "end": { "line": 94, "column": 19, "offset": 3818 }
            }
          },
          {
            "type": "element",
            "tagName": "a",
            "properties": { "href": "https://www.npmjs.com/" },
            "children": [
              {
                "type": "text",
                "value": "https://www.npmjs.com/",
                "position": {
                  "start": { "line": 94, "column": 20, "offset": 3819 },
                  "end": { "line": 94, "column": 42, "offset": 3841 }
                }
              }
            ],
            "position": {
              "start": { "line": 94, "column": 19, "offset": 3818 },
              "end": { "line": 94, "column": 43, "offset": 3842 }
            }
          }
        ],
        "position": {
          "start": { "line": 94, "column": 1, "offset": 3800 },
          "end": { "line": 94, "column": 43, "offset": 3842 }
        }
      },
      { "type": "text", "value": "\n" },
      {
        "type": "element",
        "tagName": "h3",
        "properties": { "id": "see-also", "style": "position:relative;" },
        "children": [
          {
            "type": "element",
            "tagName": "a",
            "properties": {
              "href": "#see-also",
              "aria-label": "see also permalink",
              "class": "header-link-class before"
            },
            "children": [
              {
                "type": "raw",
                "value": "<svg aria-hidden=\"true\" height=\"20\" version=\"1.1\" viewBox=\"0 0 16 16\" width=\"20\"><path fill-rule=\"evenodd\" d=\"M4 9h1v1H4c-1.5 0-3-1.69-3-3.5S2.55 3 4 3h4c1.45 0 3 1.69 3 3.5 0 1.41-.91 2.72-2 3.25V8.59c.58-.45 1-1.27 1-2.09C10 5.22 8.98 4 8 4H4c-.98 0-2 1.22-2 2.5S3 9 4 9zm9-3h-1v1h1c1 0 2 1.22 2 2.5S13.98 12 13 12H9c-.98 0-2-1.22-2-2.5 0-.83.42-1.64 1-2.09V6.25c-1.09.53-2 1.84-2 3.25C6 11.31 7.55 13 9 13h4c1.45 0 3-1.69 3-3.5S14.5 6 13 6z\"></path></svg>"
              }
            ]
          },
          {
            "type": "text",
            "value": "See also",
            "position": {
              "start": { "line": 96, "column": 5, "offset": 3848 },
              "end": { "line": 96, "column": 13, "offset": 3856 }
            }
          }
        ],
        "position": {
          "start": { "line": 96, "column": 1, "offset": 3844 },
          "end": { "line": 96, "column": 13, "offset": 3856 }
        }
      },
      { "type": "text", "value": "\n" },
      {
        "type": "element",
        "tagName": "ul",
        "properties": {},
        "children": [
          { "type": "text", "value": "\n" },
          {
            "type": "element",
            "tagName": "li",
            "properties": {},
            "children": [
              {
                "type": "element",
                "tagName": "a",
                "properties": { "href": "/cli-commands/npm-config" },
                "children": [
                  {
                    "type": "text",
                    "value": "npm config",
                    "position": {
                      "start": { "line": 98, "column": 4, "offset": 3861 },
                      "end": { "line": 98, "column": 14, "offset": 3871 }
                    }
                  }
                ],
                "position": {
                  "start": { "line": 98, "column": 3, "offset": 3860 },
                  "end": { "line": 98, "column": 41, "offset": 3898 }
                }
              }
            ],
            "position": {
              "start": { "line": 98, "column": 1, "offset": 3858 },
              "end": { "line": 98, "column": 41, "offset": 3898 }
            }
          },
          { "type": "text", "value": "\n" },
          {
            "type": "element",
            "tagName": "li",
            "properties": {},
            "children": [
              {
                "type": "element",
                "tagName": "a",
                "properties": { "href": "/using-npm/config" },
                "children": [
                  {
                    "type": "text",
                    "value": "config",
                    "position": {
                      "start": { "line": 99, "column": 4, "offset": 3902 },
                      "end": { "line": 99, "column": 10, "offset": 3908 }
                    }
                  }
                ],
                "position": {
                  "start": { "line": 99, "column": 3, "offset": 3901 },
                  "end": { "line": 99, "column": 30, "offset": 3928 }
                }
              }
            ],
            "position": {
              "start": { "line": 99, "column": 1, "offset": 3899 },
              "end": { "line": 99, "column": 30, "offset": 3928 }
            }
          },
          { "type": "text", "value": "\n" },
          {
            "type": "element",
            "tagName": "li",
            "properties": {},
            "children": [
              {
                "type": "element",
                "tagName": "a",
                "properties": { "href": "/configuring-npm/npmrc" },
                "children": [
                  {
                    "type": "text",
                    "value": "npmrc",
                    "position": {
                      "start": { "line": 100, "column": 4, "offset": 3932 },
                      "end": { "line": 100, "column": 9, "offset": 3937 }
                    }
                  }
                ],
                "position": {
                  "start": { "line": 100, "column": 3, "offset": 3931 },
                  "end": { "line": 100, "column": 34, "offset": 3962 }
                }
              }
            ],
            "position": {
              "start": { "line": 100, "column": 1, "offset": 3929 },
              "end": { "line": 100, "column": 34, "offset": 3962 }
            }
          },
          { "type": "text", "value": "\n" },
          {
            "type": "element",
            "tagName": "li",
            "properties": {},
            "children": [
              {
                "type": "element",
                "tagName": "a",
                "properties": { "href": "/using-npm/developers" },
                "children": [
                  {
                    "type": "text",
                    "value": "npm developers",
                    "position": {
                      "start": { "line": 101, "column": 4, "offset": 3966 },
                      "end": { "line": 101, "column": 18, "offset": 3980 }
                    }
                  }
                ],
                "position": {
                  "start": { "line": 101, "column": 3, "offset": 3965 },
                  "end": { "line": 101, "column": 42, "offset": 4004 }
                }
              }
            ],
            "position": {
              "start": { "line": 101, "column": 1, "offset": 3963 },
              "end": { "line": 101, "column": 42, "offset": 4004 }
            }
          },
          { "type": "text", "value": "\n" },
          {
            "type": "element",
            "tagName": "li",
            "properties": {},
            "children": [
              {
                "type": "element",
                "tagName": "a",
                "properties": { "href": "/using-npm/disputes" },
                "children": [
                  {
                    "type": "text",
                    "value": "npm disputes",
                    "position": {
                      "start": { "line": 102, "column": 4, "offset": 4008 },
                      "end": { "line": 102, "column": 16, "offset": 4020 }
                    }
                  }
                ],
                "position": {
                  "start": { "line": 102, "column": 3, "offset": 4007 },
                  "end": { "line": 102, "column": 38, "offset": 4042 }
                }
              }
            ],
            "position": {
              "start": { "line": 102, "column": 1, "offset": 4005 },
              "end": { "line": 102, "column": 38, "offset": 4042 }
            }
          },
          { "type": "text", "value": "\n" }
        ],
        "position": {
          "start": { "line": 98, "column": 1, "offset": 3858 },
          "end": { "line": 102, "column": 38, "offset": 4042 }
        }
      }
    ],
    "position": {
      "start": { "line": 1, "column": 1, "offset": 0 },
      "end": { "line": 103, "column": 1, "offset": 4043 }
    }
  }
}
